tbsp/BioUtils.py
tbsp/File.py
tbsp/__init__.py
tbsp/tbsp.py
tbsp-1.0.0.dist-info/DESCRIPTION.rst
tbsp-1.0.0.dist-info/METADATA
tbsp-1.0.0.dist-info/RECORD
tbsp-1.0.0.dist-info/WHEEL
tbsp-1.0.0.dist-info/entry_points.txt
tbsp-1.0.0.dist-info/metadata.json
tbsp-1.0.0.dist-info/top_level.txt
